pybaum/__init__.py
pybaum/_version.py
pybaum/config.py
pybaum/equality.py
pybaum/registry.py
pybaum/registry_entries.py
pybaum/tree_util.py
pybaum/typecheck.py
pybaum-0.1.2.dist-info/LICENSE
pybaum-0.1.2.dist-info/METADATA
pybaum-0.1.2.dist-info/WHEEL
pybaum-0.1.2.dist-info/top_level.txt
pybaum-0.1.2.dist-info/RECORD
